leetspeak/__init__.py
leetspeak/__main__.py
leetspeak-1.0.1.dist-info/METADATA
leetspeak-1.0.1.dist-info/WHEEL
leetspeak-1.0.1.dist-info/RECORD
