Metadata-Version: 2.1
Name: leetspeak
Version: 1.0.1
Summary: Convert text to and from leetspeak
Author: DJ Stomp
Author-email: 85457381+DJStompZone@users.noreply.github.com
Requires-Python: >=3.10,<4.0
Classifier: Programming Language :: Python :: 3
Classifier: Programming Language :: Python :: 3.10
Classifier: Programming Language :: Python :: 3.11
Classifier: Programming Language :: Python :: 3.12
Requires-Dist: pyspellchecker (>=0.8.2,<0.9.0)
